tabtools/__init__.py
tabtools/awk.py
tabtools/base.py
tabtools/files.py
tabtools/scripts.py
tabtools/utils.py
tabtools/tests/__init__.py
tabtools/tests/test_awk.py
tabtools/tests/test_base.py
tabtools/tests/test_files.py
tabtools-0.6.0.data/scripts/ttpretty
tabtools-0.6.0.data/scripts/tttail
tabtools-0.6.0.dist-info/LICENSE
tabtools-0.6.0.dist-info/METADATA
tabtools-0.6.0.dist-info/WHEEL
tabtools-0.6.0.dist-info/entry_points.txt
tabtools-0.6.0.dist-info/top_level.txt
tabtools-0.6.0.dist-info/RECORD
