Metadata-Version: 2.1
Name: tabtools
Version: 0.6.0
Summary: Tools for columnar files manipulation in command line
Home-page: https://github.com/slothai/tabtools
Author: Kirill Pavlov
Author-email: k@p99.io
License: MIT
Platform: UNKNOWN
Classifier: Development Status :: 3 - Alpha
Classifier: Environment :: Console
Classifier: License :: OSI Approved :: MIT License
Classifier: Natural Language :: English
Classifier: Operating System :: OS Independent
Classifier: Programming Language :: Python :: 3
Classifier: Topic :: Software Development :: Libraries :: Python Modules
Requires-Python: >=3.4
